{"niels.lohmann@gmail.com": [{"date": "2016-03-30T18:21:35Z", "message": "Merge pull request #227 from kevin--/kevin--/noexcept_documentation\n\nfixes #223 by updating README.md"}, {"date": "2016-03-30T18:18:34Z", "message": "fixed #225"}, {"date": "2016-03-30T18:12:55Z", "message": "Merge pull request #222 from Teemperor/fixAndroid\n\nAdded missing cerrno header to fix ERANGE compile error on android"}, {"date": "2016-03-30T17:47:08Z", "message": "added more thanks to the README file"}, {"date": "2016-03-30T17:42:54Z", "message": "better notes for Android (manually closes #215)"}, {"date": "2016-03-30T17:23:11Z", "message": "cleanup after PR #212 and PR #226"}, {"date": "2016-03-29T08:35:24Z", "message": "Merge pull request #226 from lv-zheng/fix_int64\n\nUse namespace std for int64_t and uint64_t"}, {"date": "2016-03-25T16:41:36Z", "message": "added copyright information to files to make release more self-contained"}, {"date": "2016-03-06T19:03:05Z", "message": "fixes #214"}, {"date": "2016-03-04T06:30:08Z", "message": "fixed #217"}, {"date": "2016-03-04T06:26:27Z", "message": "Merge pull request #218 from Annihil/master\n\nCorrected readme"}], "kevin.c.dixon@gmail.com": [{"date": "2016-03-30T04:41:46Z", "message": "fixes #223 by updating README.md"}], "lv.zheng.2015@gmail.com": [{"date": "2016-03-28T09:01:25Z", "message": "Use namespace std for int64_t and uint64_t\n\nAccording to the c++11 standard, the declarations are within namespace\nscope of the namespace `std'. Add `std::' to avoid unnecessary\nrequirement of implementations."}], "teemperor@gmail.com": [{"date": "2016-03-10T07:46:26Z", "message": "Added missing cerrno header to fix ERANGE c-error on android"}], "annihil53@gmail.com": [{"date": "2016-03-02T01:01:40Z", "message": "Corrected readme\n\nInternally, the elements in a map are always sorted by its key following a specific strict weak ordering criterion indicated by its internal comparison object (of type Compare).\r\nWith string type, the default comparator is alphabetical order, and thus two come after three."}]}